{
  "version": 1,
  "entries": [
    {
      "path": "action__action.yml.md",
      "hash": "e4449d0b68c26c53"
    },
    {
      "path": "demo__docguard.config.json.md",
      "hash": "7675a19e066cc3c7"
    },
    {
      "path": "demo__package.json.md",
      "hash": "5edb70d10eb9c213"
    },
    {
      "path": "demo__src__calculator.ts.md",
      "hash": "ee832235d4be6958"
    },
    {
      "path": "demo__src__types.ts.md",
      "hash": "a70f8a19a41f4f8c"
    },
    {
      "path": "demo__src__user-service.ts.md",
      "hash": "e01d59a0113e5b1b"
    },
    {
      "path": "documentation.config.schema.json.md",
      "hash": "02952949787f3cae"
    },
    {
      "path": "mcp__package.json.md",
      "hash": "188e3bf2f8de7aba"
    },
    {
      "path": "mcp__src__resources__docs.ts.md",
      "hash": "d19b61136b7a67cf"
    },
    {
      "path": "mcp__src__server.ts.md",
      "hash": "f6fbb68600a8207b"
    },
    {
      "path": "mcp__src__tools__drift.ts.md",
      "hash": "32d8423be582b838"
    },
    {
      "path": "mcp__src__tools__impact.ts.md",
      "hash": "3772c083d1fe044c"
    },
    {
      "path": "mcp__src__tools__scan.ts.md",
      "hash": "1bbd156c3e8eb87e"
    },
    {
      "path": "mcp__src__tools__validate.ts.md",
      "hash": "25fab343fb3730d8"
    },
    {
      "path": "mcp__tsconfig.json.md",
      "hash": "953b77668503a5db"
    },
    {
      "path": "package.json.md",
      "hash": "6939c526eba8aaba"
    },
    {
      "path": "packages__doc-system-agent__examples__basic-project__package.json.md",
      "hash": "2d0e5cc4819bb0bf"
    },
    {
      "path": "packages__doc-system-agent__examples__basic-project__src__calculator.ts.md",
      "hash": "23ac03954938385d"
    },
    {
      "path": "packages__doc-system-agent__package.json.md",
      "hash": "2d4a027f2957dec8"
    },
    {
      "path": "packages__doc-system-agent__src__cli__index.ts.md",
      "hash": "6c435c061ad2685a"
    },
    {
      "path": "packages__doc-system-agent__src__cli__init.ts.md",
      "hash": "d51081164734ac83"
    },
    {
      "path": "packages__doc-system-agent__src__cli__update.ts.md",
      "hash": "44492efb0eacc6a1"
    },
    {
      "path": "packages__doc-system-agent__src__constants.ts.md",
      "hash": "3523bb1fcc7cfd8e"
    },
    {
      "path": "packages__doc-system-agent__src__index.ts.md",
      "hash": "285e363d13ad8b6d"
    },
    {
      "path": "packages__doc-system-agent__src__mcp__resources__docs.ts.md",
      "hash": "c82b80c6494aa7b1"
    },
    {
      "path": "packages__doc-system-agent__src__mcp__server.ts.md",
      "hash": "8992d96b22a15296"
    },
    {
      "path": "packages__doc-system-agent__src__mcp__tools__drift.ts.md",
      "hash": "1762f06c4b469daa"
    },
    {
      "path": "packages__doc-system-agent__src__mcp__tools__impact.ts.md",
      "hash": "e7649da5245e9516"
    },
    {
      "path": "packages__doc-system-agent__src__mcp__tools__scan.ts.md",
      "hash": "5a4ffe6f22326680"
    },
    {
      "path": "packages__doc-system-agent__src__mcp__tools__validate.ts.md",
      "hash": "7ad711bf762bb208"
    },
    {
      "path": "packages__doc-system-agent__src__mcp__types.ts.md",
      "hash": "7aeaf2beb713d819"
    },
    {
      "path": "packages__doc-system-agent__tsconfig.json.md",
      "hash": "bf26f9f5ed02e992"
    },
    {
      "path": "src____tests____setup.ts.md",
      "hash": "cdf818cbba92ec39"
    },
    {
      "path": "src____tests____signature-formatter.test.ts.md",
      "hash": "4ac983c5da1299d6"
    },
    {
      "path": "src____tests____snapshot-doc-generation.test.ts.md",
      "hash": "1a3eccc0f32f00a3"
    },
    {
      "path": "src____tests____symbol-classifier.test.ts.md",
      "hash": "ae509d6cdae9fe94"
    },
    {
      "path": "src__cache__ast-cache.ts.md",
      "hash": "842deab6ec0250d4"
    },
    {
      "path": "src__cache__dependencies-cache.ts.md",
      "hash": "7561129dd871074d"
    },
    {
      "path": "src__cache__output-cache.ts.md",
      "hash": "689a92a857945a56"
    },
    {
      "path": "src__cache__signature-cache.ts.md",
      "hash": "dcd294c6b6ad6be5"
    },
    {
      "path": "src__core__async.ts.md",
      "hash": "33aa41ac824aaa19"
    },
    {
      "path": "src__core__consolidation.ts.md",
      "hash": "d2a7c18b69e587b9"
    },
    {
      "path": "src__core__git.ts.md",
      "hash": "20ed50e128b269c1"
    },
    {
      "path": "src__core__language-detection.ts.md",
      "hash": "3840b480c55907a8"
    },
    {
      "path": "src__core__scanner.ts.md",
      "hash": "73c796afe3f14b38"
    },
    {
      "path": "src__core__signature-formatter.ts.md",
      "hash": "4afbf73efc76508e"
    },
    {
      "path": "src__core__symbol-classifier.ts.md",
      "hash": "0507614f23a25a0b"
    },
    {
      "path": "src__core__symbols.ts.md",
      "hash": "df4cc97e941fa14c"
    },
    {
      "path": "src__drift__index.ts.md",
      "hash": "b74732e0668b5a41"
    },
    {
      "path": "src__extension.ts.md",
      "hash": "5cfcbb5a79f246f9"
    },
    {
      "path": "src__generator__change-report.ts.md",
      "hash": "8957dc7f2a357f85"
    },
    {
      "path": "src__generator__dependency-graph.ts.md",
      "hash": "cefb84e65e8896ff"
    },
    {
      "path": "src__generator__index.ts.md",
      "hash": "397aa4e42af306f7"
    },
    {
      "path": "src__generator__module-doc.ts.md",
      "hash": "25a23b79d2091e80"
    },
    {
      "path": "src__index__index.ts.md",
      "hash": "83beee237b85f080"
    },
    {
      "path": "src__logging__index.ts.md",
      "hash": "766ec856664da55a"
    },
    {
      "path": "src__parsers__dependencies.ts.md",
      "hash": "27edb883abcdf36e"
    },
    {
      "path": "src__parsers__json-yaml.ts.md",
      "hash": "aa0fd8def4360935"
    },
    {
      "path": "src__parsers__python.ts.md",
      "hash": "1d263ff36ead19b3"
    },
    {
      "path": "src__parsers__ts-js.ts.md",
      "hash": "fa8b9220e913da81"
    },
    {
      "path": "src__parsers__types.ts.md",
      "hash": "c3084d9c2d509210"
    },
    {
      "path": "src__ui__commands-provider.ts.md",
      "hash": "36adf9255b3b7df1"
    },
    {
      "path": "src__ui__status-bar.ts.md",
      "hash": "2640e87d62b6eeba"
    },
    {
      "path": "src__validator__index.ts.md",
      "hash": "999a0ab4c325a6db"
    },
    {
      "path": "src__validator__signature-matching.ts.md",
      "hash": "19403ffb25d2e136"
    },
    {
      "path": "src__validator__status.ts.md",
      "hash": "b535b83a4ea965f2"
    },
    {
      "path": "tsconfig.json.md",
      "hash": "dcb0a9baedb8a24e"
    },
    {
      "path": "website__package.json.md",
      "hash": "1e1a400154af637f"
    },
    {
      "path": "website__tsconfig.json.md",
      "hash": "70a8cde8e19c1744"
    },
    {
      "path": "website__vercel.json.md",
      "hash": "de6bd2875c6e6ebf"
    }
  ]
}
